ruvmedia/__init__.py
ruvmedia/const.py
ruvmedia/gql_client.py
ruvmedia/live_streams.py
ruvmedia/models.py
ruvmedia/ruv_client.py
ruvmedia-0.0.2.dist-info/METADATA
ruvmedia-0.0.2.dist-info/WHEEL
ruvmedia-0.0.2.dist-info/RECORD
